<?xml version="1.0" encoding="UTF-8"?><?xml-stylesheet type="text/xsl" href="NewResultForExcelCompare.xsl"?><TestSuite EndTime="06-08-2016 14:17:34" StartTime="06-08-2016 14:17:32" TF="2" TP="0" TotalTestCases="2"><Functionality name="Gary  Bergstrom"><TestScript EndTime="06-08-2016 14:17:33" StartTime="06-08-2016 14:17:32" TC_Status="Fail" name="Click To View Results"><Iterator no="0"><step no="1"><status>Fail</status><stepname>Investor Name</stepname><VEDA2.0>Gary  Bergstrom</VEDA2.0><VEDA1.5>GARY BERGSTROM</VEDA1.5><Difference>NA</Difference><timestamp>06-08-2016 14:17:32</timestamp></step><step no="2"><status>Pass</status><stepname>Holder Name</stepname><VEDA2.0>Gary Bergstrom</VEDA2.0><VEDA1.5>Gary Bergstrom</VEDA1.5><Difference>NA</Difference><timestamp>06-08-2016 14:17:32</timestamp></step><step no="3"><status>Pass</status><stepname>Account</stepname><VEDA2.0>AC0351</VEDA2.0><VEDA1.5>AC0351</VEDA1.5><Difference>NA</Difference><timestamp>06-08-2016 14:17:32</timestamp></step><step no="4"><status>Pass</status><stepname>Mgt Fee %</stepname><VEDA2.0>0%</VEDA2.0><VEDA1.5>0%</VEDA1.5><Difference>0%</Difference><timestamp>06-08-2016 14:17:32</timestamp></step><step no="5"><status>Pass</status><stepname>Perf Fees %</stepname><VEDA2.0>0%</VEDA2.0><VEDA1.5>0%</VEDA1.5><Difference>0%</Difference><timestamp>06-08-2016 14:17:32</timestamp></step><step no="6"><status>Pass</status><stepname>Units (Opening)</stepname><VEDA2.0>0.0000</VEDA2.0><VEDA1.5>0.0000</VEDA1.5><Difference>0.0000</Difference><timestamp>06-08-2016 14:17:32</timestamp></step><step no="7"><status>Fail</status><stepname>Gross Asset Value (Opening)</stepname><VEDA2.0>41692645.2287</VEDA2.0><VEDA1.5>NA</VEDA1.5><Difference>NA</Difference><timestamp>06-08-2016 14:17:32</timestamp></step><step no="8"><status>Fail</status><stepname>Net Asset Value (Opening)</stepname><VEDA2.0>41692645.2287</VEDA2.0><VEDA1.5>0.0000</VEDA1.5><Difference>41692645.2287</Difference><timestamp>06-08-2016 14:17:32</timestamp></step><step no="9"><status>Fail</status><stepname>Additions</stepname><VEDA2.0>0.0000</VEDA2.0><VEDA1.5>41692644.9689</VEDA1.5><Difference>-41692644.9689</Difference><timestamp>06-08-2016 14:17:32</timestamp></step><step no="10"><status>Fail</status><stepname>Added Units</stepname><VEDA2.0>0.0000</VEDA2.0><VEDA1.5>41692644.9689</VEDA1.5><Difference>-41692644.9689</Difference><timestamp>06-08-2016 14:17:32</timestamp></step><step no="11"><status>Pass</status><stepname>Redemptions</stepname><VEDA2.0>0.0000</VEDA2.0><VEDA1.5>0.0000</VEDA1.5><Difference>0.0000</Difference><timestamp>06-08-2016 14:17:32</timestamp></step><step no="12"><status>Pass</status><stepname>Redeemed Units</stepname><VEDA2.0>0.0000</VEDA2.0><VEDA1.5>0.0000</VEDA1.5><Difference>0.0000</Difference><timestamp>06-08-2016 14:17:32</timestamp></step><step no="13"><status>Pass</status><stepname>Transfer</stepname><VEDA2.0>0.0000</VEDA2.0><VEDA1.5>0.0000</VEDA1.5><Difference>0.0000</Difference><timestamp>06-08-2016 14:17:32</timestamp></step><step no="14"><status>Pass</status><stepname>Transfer Units</stepname><VEDA2.0>0.0000</VEDA2.0><VEDA1.5>0.0000</VEDA1.5><Difference>0.0000</Difference><timestamp>06-08-2016 14:17:32</timestamp></step><step no="15"><status>Pass</status><stepname>Switch</stepname><VEDA2.0>0.0000</VEDA2.0><VEDA1.5>0.0000</VEDA1.5><Difference>0.0000</Difference><timestamp>06-08-2016 14:17:32</timestamp></step><step no="16"><status>Pass</status><stepname>Switch Units</stepname><VEDA2.0>0.0000</VEDA2.0><VEDA1.5>0.0000</VEDA1.5><Difference>0.0000</Difference><timestamp>06-08-2016 14:17:32</timestamp></step><step no="17"><status>Pass</status><stepname>Exchange</stepname><VEDA2.0>0.0000</VEDA2.0><VEDA1.5>0.0000</VEDA1.5><Difference>0.0000</Difference><timestamp>06-08-2016 14:17:32</timestamp></step><step no="18"><status>Pass</status><stepname>Exchange Units</stepname><VEDA2.0>0.0000</VEDA2.0><VEDA1.5>0.0000</VEDA1.5><Difference>0.0000</Difference><timestamp>06-08-2016 14:17:32</timestamp></step><step no="19"><status>Pass</status><stepname>Adjusted Units</stepname><VEDA2.0>0.0000</VEDA2.0><VEDA1.5>0.0000</VEDA1.5><Difference>0.0000</Difference><timestamp>06-08-2016 14:17:32</timestamp></step><step no="20"><status>Fail</status><stepname>Adjusted Gross Asset Value(Opening)</stepname><VEDA2.0>41692645.2287</VEDA2.0><VEDA1.5>0.0000</VEDA1.5><Difference>41692645.2287</Difference><timestamp>06-08-2016 14:17:32</timestamp></step><step no="21"><status>Fail</status><stepname>OwnerShip %</stepname><VEDA2.0>95.47%</VEDA2.0><VEDA1.5>0%</VEDA1.5><Difference>95.47%</Difference><timestamp>06-08-2016 14:17:32</timestamp></step><step no="22"><status>Fail</status><stepname>Even Allocation Amount</stepname><VEDA2.0>317152.2907</VEDA2.0><VEDA1.5>41692644.9689</VEDA1.5><Difference>-41375492.6782</Difference><timestamp>06-08-2016 14:17:32</timestamp></step><step no="23"><status>Fail</status><stepname>New Issue P/L</stepname><VEDA2.0>0.0000</VEDA2.0><VEDA1.5>0.9547</VEDA1.5><Difference>-0.9547</Difference><timestamp>06-08-2016 14:17:32</timestamp></step><step no="24"><status>Fail</status><stepname>Un Even Allocation Amount</stepname><VEDA2.0>0.0000</VEDA2.0><VEDA1.5>317152.4914</VEDA1.5><Difference>-317152.4914</Difference><timestamp>06-08-2016 14:17:32</timestamp></step><step no="25"><status>Fail</status><stepname>Current PTD Gross P/L</stepname><VEDA2.0>317152.2907</VEDA2.0><VEDA1.5>0.0000</VEDA1.5><Difference>317152.2907</Difference><timestamp>06-08-2016 14:17:32</timestamp></step><step no="26"><status>Pass</status><stepname>Custom Fess</stepname><VEDA2.0>0.0000</VEDA2.0><VEDA1.5>0.0000</VEDA1.5><Difference>0.0000</Difference><timestamp>06-08-2016 14:17:32</timestamp></step><step no="27"><status>Fail</status><stepname>Management Fee</stepname><VEDA2.0>0.0000</VEDA2.0><VEDA1.5>317152.4914</VEDA1.5><Difference>-317152.4914</Difference><timestamp>06-08-2016 14:17:32</timestamp></step><step no="28"><status>Pass</status><stepname>Management Fee Waiver</stepname><VEDA2.0>0.0000</VEDA2.0><VEDA1.5>0.0000</VEDA1.5><Difference>0.0000</Difference><timestamp>06-08-2016 14:17:32</timestamp></step><step no="29"><status>Pass</status><stepname>Total Management Fees</stepname><VEDA2.0>0.0000</VEDA2.0><VEDA1.5>0.0000</VEDA1.5><Difference>0.0000</Difference><timestamp>06-08-2016 14:17:32</timestamp></step><step no="30"><status>Fail</status><stepname>Gross Asset Value (Closing)</stepname><VEDA2.0>42009797.5193</VEDA2.0><VEDA1.5>0.0000</VEDA1.5><Difference>42009797.5193</Difference><timestamp>06-08-2016 14:17:32</timestamp></step><step no="31"><status>Pass</status><stepname>Performance Fees</stepname><VEDA2.0>0.0000</VEDA2.0><VEDA1.5>0.0000</VEDA1.5><Difference>0.0000</Difference><timestamp>06-08-2016 14:17:32</timestamp></step><step no="32"><status>Fail</status><stepname>Performance Cumulative</stepname><VEDA2.0>0.0000</VEDA2.0><VEDA1.5>42009797.4603</VEDA1.5><Difference>-42009797.4603</Difference><timestamp>06-08-2016 14:17:32</timestamp></step><step no="33"><status>Fail</status><stepname>Net PTD Performance</stepname><VEDA2.0>317152.2907</VEDA2.0><VEDA1.5>0.0000</VEDA1.5><Difference>317152.2907</Difference><timestamp>06-08-2016 14:17:32</timestamp></step><step no="34"><status>Fail</status><stepname>Net Asset Value(Closing)</stepname><VEDA2.0>42009797.5193</VEDA2.0><VEDA1.5>0.0000</VEDA1.5><Difference>42009797.5193</Difference><timestamp>06-08-2016 14:17:32</timestamp></step><step no="35"><status>Fail</status><stepname>Units(Closing)</stepname><VEDA2.0>0.0000</VEDA2.0><VEDA1.5>317152.4914</VEDA1.5><Difference>-317152.4914</Difference><timestamp>06-08-2016 14:17:32</timestamp></step><step no="36"><status>Fail</status><stepname>NAV per unit</stepname><VEDA2.0>0.0000</VEDA2.0><VEDA1.5>42009797.4603</VEDA1.5><Difference>-42009797.4603</Difference><timestamp>06-08-2016 14:17:32</timestamp></step><step no="37"><status>Fail</status><stepname>Gross PTD %</stepname><VEDA2.0>1.52%</VEDA2.0><VEDA1.5>0%</VEDA1.5><Difference>1.52%</Difference><timestamp>06-08-2016 14:17:32</timestamp></step><step no="38"><status>Fail</status><stepname>Gross MTD %</stepname><VEDA2.0>1.52%</VEDA2.0><VEDA1.5>0%</VEDA1.5><Difference>1.52%</Difference><timestamp>06-08-2016 14:17:32</timestamp></step><step no="39"><status>Fail</status><stepname>Gross QTD %</stepname><VEDA2.0>3.27%</VEDA2.0><VEDA1.5>0%</VEDA1.5><Difference>3.27%</Difference><timestamp>06-08-2016 14:17:32</timestamp></step><step no="40"><status>Fail</status><stepname>Gross YTD %</stepname><VEDA2.0>3.27%</VEDA2.0><VEDA1.5>0.76%</VEDA1.5><Difference>2.51%</Difference><timestamp>06-08-2016 14:17:33</timestamp></step><step no="41"><status>Fail</status><stepname>Gross ITD %</stepname><VEDA2.0>-7.82%</VEDA2.0><VEDA1.5>1.63%</VEDA1.5><Difference>-9.45%</Difference><timestamp>06-08-2016 14:17:33</timestamp></step><step no="42"><status>Fail</status><stepname>Net PTD</stepname><VEDA2.0>1.52%</VEDA2.0><VEDA1.5>1.63%</VEDA1.5><Difference>-0.11%</Difference><timestamp>06-08-2016 14:17:33</timestamp></step><step no="43"><status>Fail</status><stepname>Net MTD</stepname><VEDA2.0>1.52%</VEDA2.0><VEDA1.5>-7.96%</VEDA1.5><Difference>9.48%</Difference><timestamp>06-08-2016 14:17:33</timestamp></step><step no="44"><status>Fail</status><stepname>Net QTD</stepname><VEDA2.0>3.27%</VEDA2.0><VEDA1.5>0%</VEDA1.5><Difference>3.27%</Difference><timestamp>06-08-2016 14:17:33</timestamp></step><step no="45"><status>Fail</status><stepname>Net YTD</stepname><VEDA2.0>3.27%</VEDA2.0><VEDA1.5>0.76%</VEDA1.5><Difference>2.51%</Difference><timestamp>06-08-2016 14:17:33</timestamp></step><step no="46"><status>Fail</status><stepname>Net ITD</stepname><VEDA2.0>-7.82%</VEDA2.0><VEDA1.5>1.63%</VEDA1.5><Difference>-9.45%</Difference><timestamp>06-08-2016 14:17:33</timestamp></step><step no="47"><status>Fail</status><stepname>Hurdle Amount</stepname><VEDA2.0>0.0000</VEDA2.0><VEDA1.5>0.0163</VEDA1.5><Difference>-0.0163</Difference><timestamp>06-08-2016 14:17:33</timestamp></step></Iterator></TestScript></Functionality><Functionality name="Trafalgar Partners LLC"><TestScript EndTime="06-08-2016 14:17:34" StartTime="06-08-2016 14:17:33" TC_Status="Fail" name="Click To View Results"><Iterator no="0"><step no="1"><status>Pass</status><stepname>Investor Name</stepname><VEDA2.0>Trafalgar Partners LLC</VEDA2.0><VEDA1.5>TRAFALGAR PARTNERS LLC</VEDA1.5><Difference>NA</Difference><timestamp>06-08-2016 14:17:33</timestamp></step><step no="2"><status>Pass</status><stepname>Holder Name</stepname><VEDA2.0>Trafalgar Partners LLC</VEDA2.0><VEDA1.5>Trafalgar Partners LLC</VEDA1.5><Difference>NA</Difference><timestamp>06-08-2016 14:17:33</timestamp></step><step no="3"><status>Pass</status><stepname>Account</stepname><VEDA2.0>AC0375</VEDA2.0><VEDA1.5>AC0375</VEDA1.5><Difference>NA</Difference><timestamp>06-08-2016 14:17:33</timestamp></step><step no="4"><status>Pass</status><stepname>Mgt Fee %</stepname><VEDA2.0>0%</VEDA2.0><VEDA1.5>0%</VEDA1.5><Difference>0%</Difference><timestamp>06-08-2016 14:17:33</timestamp></step><step no="5"><status>Pass</status><stepname>Perf Fees %</stepname><VEDA2.0>0%</VEDA2.0><VEDA1.5>0%</VEDA1.5><Difference>0%</Difference><timestamp>06-08-2016 14:17:33</timestamp></step><step no="6"><status>Pass</status><stepname>Units (Opening)</stepname><VEDA2.0>0.0000</VEDA2.0><VEDA1.5>0.0000</VEDA1.5><Difference>0.0000</Difference><timestamp>06-08-2016 14:17:33</timestamp></step><step no="7"><status>Fail</status><stepname>Gross Asset Value (Opening)</stepname><VEDA2.0>1977175.3613</VEDA2.0><VEDA1.5>NA</VEDA1.5><Difference>NA</Difference><timestamp>06-08-2016 14:17:33</timestamp></step><step no="8"><status>Fail</status><stepname>Net Asset Value (Opening)</stepname><VEDA2.0>1977175.3613</VEDA2.0><VEDA1.5>0.0000</VEDA1.5><Difference>1977175.3613</Difference><timestamp>06-08-2016 14:17:33</timestamp></step><step no="9"><status>Fail</status><stepname>Additions</stepname><VEDA2.0>0.0000</VEDA2.0><VEDA1.5>1977175.3211</VEDA1.5><Difference>-1977175.3211</Difference><timestamp>06-08-2016 14:17:33</timestamp></step><step no="10"><status>Fail</status><stepname>Added Units</stepname><VEDA2.0>0.0000</VEDA2.0><VEDA1.5>1977175.3211</VEDA1.5><Difference>-1977175.3211</Difference><timestamp>06-08-2016 14:17:33</timestamp></step><step no="11"><status>Pass</status><stepname>Redemptions</stepname><VEDA2.0>0.0000</VEDA2.0><VEDA1.5>0.0000</VEDA1.5><Difference>0.0000</Difference><timestamp>06-08-2016 14:17:33</timestamp></step><step no="12"><status>Pass</status><stepname>Redeemed Units</stepname><VEDA2.0>0.0000</VEDA2.0><VEDA1.5>0.0000</VEDA1.5><Difference>0.0000</Difference><timestamp>06-08-2016 14:17:33</timestamp></step><step no="13"><status>Pass</status><stepname>Transfer</stepname><VEDA2.0>0.0000</VEDA2.0><VEDA1.5>0.0000</VEDA1.5><Difference>0.0000</Difference><timestamp>06-08-2016 14:17:33</timestamp></step><step no="14"><status>Pass</status><stepname>Transfer Units</stepname><VEDA2.0>0.0000</VEDA2.0><VEDA1.5>0.0000</VEDA1.5><Difference>0.0000</Difference><timestamp>06-08-2016 14:17:33</timestamp></step><step no="15"><status>Pass</status><stepname>Switch</stepname><VEDA2.0>0.0000</VEDA2.0><VEDA1.5>0.0000</VEDA1.5><Difference>0.0000</Difference><timestamp>06-08-2016 14:17:33</timestamp></step><step no="16"><status>Pass</status><stepname>Switch Units</stepname><VEDA2.0>0.0000</VEDA2.0><VEDA1.5>0.0000</VEDA1.5><Difference>0.0000</Difference><timestamp>06-08-2016 14:17:33</timestamp></step><step no="17"><status>Pass</status><stepname>Exchange</stepname><VEDA2.0>0.0000</VEDA2.0><VEDA1.5>0.0000</VEDA1.5><Difference>0.0000</Difference><timestamp>06-08-2016 14:17:33</timestamp></step><step no="18"><status>Pass</status><stepname>Exchange Units</stepname><VEDA2.0>0.0000</VEDA2.0><VEDA1.5>0.0000</VEDA1.5><Difference>0.0000</Difference><timestamp>06-08-2016 14:17:33</timestamp></step><step no="19"><status>Pass</status><stepname>Adjusted Units</stepname><VEDA2.0>0.0000</VEDA2.0><VEDA1.5>0.0000</VEDA1.5><Difference>0.0000</Difference><timestamp>06-08-2016 14:17:33</timestamp></step><step no="20"><status>Fail</status><stepname>Adjusted Gross Asset Value(Opening)</stepname><VEDA2.0>1977175.3613</VEDA2.0><VEDA1.5>0.0000</VEDA1.5><Difference>1977175.3613</Difference><timestamp>06-08-2016 14:17:33</timestamp></step><step no="21"><status>Fail</status><stepname>OwnerShip %</stepname><VEDA2.0>4.53%</VEDA2.0><VEDA1.5>0%</VEDA1.5><Difference>4.53%</Difference><timestamp>06-08-2016 14:17:33</timestamp></step><step no="22"><status>Fail</status><stepname>Even Allocation Amount</stepname><VEDA2.0>15040.1993</VEDA2.0><VEDA1.5>1977175.3211</VEDA1.5><Difference>-1962135.1218</Difference><timestamp>06-08-2016 14:17:33</timestamp></step><step no="23"><status>Fail</status><stepname>New Issue P/L</stepname><VEDA2.0>0.0000</VEDA2.0><VEDA1.5>0.0453</VEDA1.5><Difference>-0.0453</Difference><timestamp>06-08-2016 14:17:33</timestamp></step><step no="24"><status>Fail</status><stepname>Un Even Allocation Amount</stepname><VEDA2.0>0.0000</VEDA2.0><VEDA1.5>15040.2086</VEDA1.5><Difference>-15040.2086</Difference><timestamp>06-08-2016 14:17:33</timestamp></step><step no="25"><status>Fail</status><stepname>Current PTD Gross P/L</stepname><VEDA2.0>15040.1993</VEDA2.0><VEDA1.5>0.0000</VEDA1.5><Difference>15040.1993</Difference><timestamp>06-08-2016 14:17:33</timestamp></step><step no="26"><status>Pass</status><stepname>Custom Fess</stepname><VEDA2.0>0.0000</VEDA2.0><VEDA1.5>0.0000</VEDA1.5><Difference>0.0000</Difference><timestamp>06-08-2016 14:17:33</timestamp></step><step no="27"><status>Fail</status><stepname>Management Fee</stepname><VEDA2.0>0.0000</VEDA2.0><VEDA1.5>15040.2086</VEDA1.5><Difference>-15040.2086</Difference><timestamp>06-08-2016 14:17:33</timestamp></step><step no="28"><status>Pass</status><stepname>Management Fee Waiver</stepname><VEDA2.0>0.0000</VEDA2.0><VEDA1.5>0.0000</VEDA1.5><Difference>0.0000</Difference><timestamp>06-08-2016 14:17:33</timestamp></step><step no="29"><status>Pass</status><stepname>Total Management Fees</stepname><VEDA2.0>0.0000</VEDA2.0><VEDA1.5>0.0000</VEDA1.5><Difference>0.0000</Difference><timestamp>06-08-2016 14:17:33</timestamp></step><step no="30"><status>Fail</status><stepname>Gross Asset Value (Closing)</stepname><VEDA2.0>1992215.5607</VEDA2.0><VEDA1.5>0.0000</VEDA1.5><Difference>1992215.5607</Difference><timestamp>06-08-2016 14:17:33</timestamp></step><step no="31"><status>Pass</status><stepname>Performance Fees</stepname><VEDA2.0>0.0000</VEDA2.0><VEDA1.5>0.0000</VEDA1.5><Difference>0.0000</Difference><timestamp>06-08-2016 14:17:33</timestamp></step><step no="32"><status>Fail</status><stepname>Performance Cumulative</stepname><VEDA2.0>0.0000</VEDA2.0><VEDA1.5>1992215.5297</VEDA1.5><Difference>-1992215.5297</Difference><timestamp>06-08-2016 14:17:33</timestamp></step><step no="33"><status>Fail</status><stepname>Net PTD Performance</stepname><VEDA2.0>15040.1993</VEDA2.0><VEDA1.5>0.0000</VEDA1.5><Difference>15040.1993</Difference><timestamp>06-08-2016 14:17:33</timestamp></step><step no="34"><status>Fail</status><stepname>Net Asset Value(Closing)</stepname><VEDA2.0>1992215.5607</VEDA2.0><VEDA1.5>0.0000</VEDA1.5><Difference>1992215.5607</Difference><timestamp>06-08-2016 14:17:33</timestamp></step><step no="35"><status>Fail</status><stepname>Units(Closing)</stepname><VEDA2.0>0.0000</VEDA2.0><VEDA1.5>15040.2086</VEDA1.5><Difference>-15040.2086</Difference><timestamp>06-08-2016 14:17:33</timestamp></step><step no="36"><status>Fail</status><stepname>NAV per unit</stepname><VEDA2.0>0.0000</VEDA2.0><VEDA1.5>1992215.5297</VEDA1.5><Difference>-1992215.5297</Difference><timestamp>06-08-2016 14:17:33</timestamp></step><step no="37"><status>Fail</status><stepname>Gross PTD %</stepname><VEDA2.0>0.76%</VEDA2.0><VEDA1.5>0%</VEDA1.5><Difference>0.76%</Difference><timestamp>06-08-2016 14:17:33</timestamp></step><step no="38"><status>Fail</status><stepname>Gross MTD %</stepname><VEDA2.0>0.76%</VEDA2.0><VEDA1.5>0%</VEDA1.5><Difference>0.76%</Difference><timestamp>06-08-2016 14:17:33</timestamp></step><step no="39"><status>Fail</status><stepname>Gross QTD %</stepname><VEDA2.0>1.63%</VEDA2.0><VEDA1.5>0%</VEDA1.5><Difference>1.63%</Difference><timestamp>06-08-2016 14:17:33</timestamp></step><step no="40"><status>Fail</status><stepname>Gross YTD %</stepname><VEDA2.0>1.63%</VEDA2.0><VEDA1.5>0.76%</VEDA1.5><Difference>0.87%</Difference><timestamp>06-08-2016 14:17:33</timestamp></step><step no="41"><status>Fail</status><stepname>Gross ITD %</stepname><VEDA2.0>-0.39%</VEDA2.0><VEDA1.5>1.63%</VEDA1.5><Difference>-2.02%</Difference><timestamp>06-08-2016 14:17:33</timestamp></step><step no="42"><status>Fail</status><stepname>Net PTD</stepname><VEDA2.0>0.76%</VEDA2.0><VEDA1.5>1.63%</VEDA1.5><Difference>-0.87%</Difference><timestamp>06-08-2016 14:17:33</timestamp></step><step no="43"><status>Fail</status><stepname>Net MTD</stepname><VEDA2.0>0.76%</VEDA2.0><VEDA1.5>-0.39%</VEDA1.5><Difference>1.15%</Difference><timestamp>06-08-2016 14:17:33</timestamp></step><step no="44"><status>Fail</status><stepname>Net QTD</stepname><VEDA2.0>1.63%</VEDA2.0><VEDA1.5>0%</VEDA1.5><Difference>1.63%</Difference><timestamp>06-08-2016 14:17:33</timestamp></step><step no="45"><status>Fail</status><stepname>Net YTD</stepname><VEDA2.0>1.63%</VEDA2.0><VEDA1.5>0.76%</VEDA1.5><Difference>0.87%</Difference><timestamp>06-08-2016 14:17:34</timestamp></step><step no="46"><status>Fail</status><stepname>Net ITD</stepname><VEDA2.0>-0.39%</VEDA2.0><VEDA1.5>1.63%</VEDA1.5><Difference>-2.02%</Difference><timestamp>06-08-2016 14:17:34</timestamp></step><step no="47"><status>Fail</status><stepname>Hurdle Amount</stepname><VEDA2.0>0.0000</VEDA2.0><VEDA1.5>0.0163</VEDA1.5><Difference>-0.0163</Difference><timestamp>06-08-2016 14:17:34</timestamp></step></Iterator></TestScript></Functionality></TestSuite>